{
  "$schema": "https://signng.dev/schema/registry-item.json",
  "name": "toggle-group",
  "type": "registry:ui",
  "description": "Roving toggle group (single/multiple, role=group, arrow nav) reusing toggle variants.",
  "dependencies": [],
  "registryDependencies": [
    "utils",
    "toggle"
  ],
  "files": [
    {
      "path": "src/components/ui/toggle-group.ts",
      "target": "src/components/ui/toggle-group.ts",
      "type": "registry:ui",
      "content": "import {\n  Directive,\n  ElementRef,\n  booleanAttribute,\n  computed,\n  contentChildren,\n  forwardRef,\n  inject,\n  input,\n  model,\n  signal,\n} from '@angular/core';\nimport { cn } from '@/lib/utils';\nimport { toggleVariants } from '@/components/ui/toggle';\n\n/**\n * ToggleGroup (helm compound) — a roving-tabindex group of toggle buttons, single or multiple\n * selection. role=group; one tab stop, Arrow keys roam (APG toolbar), Space/Enter (native button)\n * toggles. forwardRef breaks the item<->group DI cycle. Value is always a string[] (single = 0/1).\n */\n@Directive({\n  selector: 'button[signngToggleItem]',\n  host: {\n    type: 'button',\n    '[attr.aria-pressed]': 'selected()',\n    '[attr.data-state]': 'selected() ? \"on\" : \"off\"',\n    '[attr.tabindex]': 'tabindex()',\n    '[disabled]': 'isDisabled() ? true : null',\n    '[class]': 'cls()',\n    '(click)': 'toggle()',\n  },\n})\nexport class SignngToggleItem {\n  private readonly group = inject<SignngToggleGroup>(forwardRef(() => SignngToggleGroup));\n  private readonly host = inject<ElementRef<HTMLButtonElement>>(ElementRef);\n\n  readonly value = input.required<string>();\n  readonly disabled = input(false, { transform: booleanAttribute });\n  readonly variant = input<'default' | 'outline'>('outline');\n  readonly size = input<'default' | 'sm' | 'lg'>('default');\n  readonly class = input('');\n\n  readonly selected = computed(() => this.group.isSelected(this.value()));\n  readonly isDisabled = computed(() => this.group.disabled() || this.disabled());\n  readonly tabindex = computed(() => {\n    if (this.isDisabled()) return -1;\n    return this.group.tabbableValue() === this.value() ? 0 : -1;\n  });\n\n  protected readonly cls = computed(() =>\n    cn(toggleVariants({ variant: this.variant(), size: this.size() }), this.class()),\n  );\n\n  toggle(): void {\n    if (this.isDisabled()) return;\n    this.group.toggle(this.value());\n    this.group.setFocused(this.value());\n  }\n  focus(): void {\n    this.host.nativeElement.focus();\n  }\n}\n\n@Directive({\n  selector: '[signngToggleGroup]',\n  host: {\n    role: 'group',\n    class: 'inline-flex gap-1',\n    '(keydown)': 'onKeydown($event)',\n  },\n})\nexport class SignngToggleGroup {\n  /** Selected values (single-select still uses an array of 0 or 1). */\n  readonly value = model<string[]>([]);\n  readonly type = input<'single' | 'multiple'>('single');\n  readonly disabled = input(false, { transform: booleanAttribute });\n\n  readonly items = contentChildren(SignngToggleItem);\n  private readonly focused = signal<string | null>(null);\n\n  readonly tabbableValue = computed(() => {\n    const f = this.focused();\n    const enabled = this.items().filter((i) => !i.isDisabled());\n    if (f && enabled.some((i) => i.value() === f)) return f;\n    return enabled[0]?.value() ?? null;\n  });\n\n  isSelected(v: string): boolean {\n    return this.value().includes(v);\n  }\n\n  toggle(v: string): void {\n    const cur = this.value();\n    if (this.type() === 'single') {\n      this.value.set(cur.includes(v) ? [] : [v]);\n    } else {\n      this.value.set(cur.includes(v) ? cur.filter((x) => x !== v) : [...cur, v]);\n    }\n  }\n\n  setFocused(v: string): void {\n    this.focused.set(v);\n  }\n\n  protected onKeydown(event: KeyboardEvent): void {\n    const enabled = this.items().filter((i) => !i.isDisabled());\n    if (!enabled.length) return;\n    const cur = Math.max(0, enabled.findIndex((i) => i.value() === this.tabbableValue()));\n    let target: SignngToggleItem | undefined;\n    switch (event.key) {\n      case 'ArrowRight':\n      case 'ArrowDown':\n        target = enabled[(cur + 1) % enabled.length];\n        break;\n      case 'ArrowLeft':\n      case 'ArrowUp':\n        target = enabled[(cur - 1 + enabled.length) % enabled.length];\n        break;\n      case 'Home':\n        target = enabled[0];\n        break;\n      case 'End':\n        target = enabled[enabled.length - 1];\n        break;\n      default:\n        return;\n    }\n    event.preventDefault();\n    this.setFocused(target.value());\n    target.focus();\n  }\n}\n\nexport const SIGNNG_TOGGLE_GROUP = [SignngToggleGroup, SignngToggleItem] as const;\n",
      "integrity": "sha256-apTknLE0SJExXJ7/IokBSzkjKmqrLFezirBFdrGoxBY="
    }
  ],
  "integrity": "sha256-YyrDd7BSRYS9bQtHImhWT8xa6XdXV56IZtOjIrZ6ghg="
}